idkwhttph/__init__.py
idkwhttph-0.4.4.dist-info/WHEEL
idkwhttph-0.4.4.dist-info/METADATA
idkwhttph-0.4.4.dist-info/RECORD
